functions_by_sayyora007/README.md
functions_by_sayyora007/math_functions.py
functions_by_sayyora007-0.3.0.dist-info/WHEEL
functions_by_sayyora007-0.3.0.dist-info/METADATA
functions_by_sayyora007-0.3.0.dist-info/RECORD
